custom_exception_logger/__init__.py
custom_exception_logger/logger.py
custom_exception_logger-0.1.dist-info/METADATA
custom_exception_logger-0.1.dist-info/WHEEL
custom_exception_logger-0.1.dist-info/top_level.txt
custom_exception_logger-0.1.dist-info/RECORD
